README.rst
setup.py
aioflock/__init__.py
aioflock/exceptions.py
aioflock/lock.py
aioflock.egg-info/PKG-INFO
aioflock.egg-info/SOURCES.txt
aioflock.egg-info/dependency_links.txt
aioflock.egg-info/requires.txt
aioflock.egg-info/top_level.txt
tests/__init__.py
tests/test_simple.py