Metadata-Version: 1.1
Name: aioflock
Version: 0.0.1
Summary: File support for asyncio.
Home-page: https://github.com/kolko/aioflock
Author: Krat Nikolay
Author-email: @gmail.com
License: Apache 2.0
Platform: UNKNOWN
Classifier: Development Status :: 4 - Beta
Classifier: Intended Audience :: Developers
Classifier: License :: OSI Approved :: Apache Software License
Classifier: Programming Language :: Python :: 3.3
Classifier: Programming Language :: Python :: 3.4
Classifier: Topic :: System :: Filesystems
